pyfactorial/__init__.py
pyfactorial/module.py
pyfactorial-0.0.1.dist-info/METADATA
pyfactorial-0.0.1.dist-info/WHEEL
pyfactorial-0.0.1.dist-info/licenses/LICENSE
pyfactorial-0.0.1.dist-info/RECORD
