Metadata-Version: 2.1
Name: pyfactorial
Version: 0.0.1
Summary: A Python package for calculating factorials
Project-URL: Homepage, https://github.com/Rakshanda26/pyfactorial
Project-URL: Bug Tracker, https://github.com/Rakshanda26/pyfactorial/issues
Author-email: Rakshanda Mahajan <rakshandamm123@gmail.com>
License-File: LICENSE
Classifier: License :: OSI Approved :: MIT License
Classifier: Operating System :: OS Independent
Classifier: Programming Language :: Python :: 3
Requires-Python: >=3.7
